stabilock4040/__init__.py
stabilock4040/stabilock4040.py
stabilock4040-0.0.2.dist-info/LICENSE
stabilock4040-0.0.2.dist-info/METADATA
stabilock4040-0.0.2.dist-info/WHEEL
stabilock4040-0.0.2.dist-info/top_level.txt
stabilock4040-0.0.2.dist-info/RECORD
