Metadata-Version: 2.1
Name: stabilock4040
Version: 0.0.2
Summary: Driver for the Schlumberger/Wavetek Stabilock 4040 Communications Test Set
Home-page: https://gitlab.com/aebrookes/stabilock-4040
Author: Adam Brookes
Author-email: adam@adambrookes.co.uk
License: UNKNOWN
Platform: UNKNOWN
Classifier: Programming Language :: Python :: 3
Classifier: License :: OSI Approved :: MIT License
Classifier: Operating System :: OS Independent
Requires-Python: >=3.8
Requires-Dist: pyvisa
